{
  "dayCounts": {
    "2023/4/8": 601,
    "2023/4/10": 24,
    "2023/4/11": 192,
    "2023/4/12": 541,
    "2023/4/13": 118,
    "2023/4/14": 98,
    "2023/4/15": 961,
    "2023/4/18": 186,
    "2023/4/20": 3,
    "2023/4/21": 977,
    "2023/4/23": 0,
    "2023/4/24": 1636,
    "2023/4/26": 71,
    "2023/4/27": 694
  },
  "todaysWordCount": {
    "HG-Meditation/Practise/0. Index and Notes.md": {
      "initial": 307,
      "current": 376
    },
    "02.Programming/00. Leetcode/383. Ransom Note.md": {
      "initial": 124,
      "current": 250
    },
    "z.Template/leetcode Note.md": {
      "initial": 32,
      "current": 32
    },
    "02.Programming/00. Leetcode/235. Lowest Common Ancestor of a Binary Search Tree.md": {
      "initial": 0,
      "current": 499
    }
  }
}